winutils.py
pywinutils-0.2.dist-info/DESCRIPTION.rst
pywinutils-0.2.dist-info/METADATA
pywinutils-0.2.dist-info/RECORD
pywinutils-0.2.dist-info/WHEEL
pywinutils-0.2.dist-info/metadata.json
pywinutils-0.2.dist-info/top_level.txt
