Metadata-Version: 2.0
Name: pywinutils
Version: 0.2
Summary: Copy move and delete files using the built in Window's progress dialog
Home-page: http://github.com/frmdstryr/pywinutils
Author: frmdstryr
Author-email: frmdstryr@gmail.com
License: MIT
Platform: UNKNOWN
Requires: pywin32
Requires-Dist: pywin32 (>=218)
